{
  "a_comp_cor_00": {
    "CumulativeVarianceExplained": 0.1157242649,
    "Mask": "combined",
    "Method": "aCompCor",
    "Retained": true,
    "SingularValue": 167.6068772918,
    "VarianceExplained": 0.1157242649
  },
  "a_comp_cor_01": {
    "CumulativeVarianceExplained": 0.1603934266,
    "Mask": "combined",
    "Method": "aCompCor",
    "Retained": true,
    "SingularValue": 104.1318346239,
    "VarianceExplained": 0.0446691616
  },
  "a_comp_cor_02": {
    "CumulativeVarianceExplained": 0.183127137,
    "Mask": "combined",
    "Method": "aCompCor",
    "Retained": true,
    "SingularValue": 74.2873353784,
    "VarianceExplained": 0.0227337104
  },
  "a_comp_cor_03": {
    "CumulativeVarianceExplained": 0.2032465127,
    "Mask": "combined",
    "Method": "aCompCor",
    "Retained": true,
    "SingularValue": 69.8854667839,
    "VarianceExplained": 0.0201193758
  },
  "a_comp_cor_04": {
    "CumulativeVarianceExplained": 0.2224577979,
    "Mask": "combined",
    "Method": "aCompCor",
    "Retained": true,
    "SingularValue": 68.2901125891,
    "VarianceExplained": 0.0192112852
  },
  "a_comp_cor_05": {
    "CumulativeVarianceExplained": 0.239905712,
    "Mask": "combined",
    "Method": "aCompCor",
    "Retained": true,
    "SingularValue": 65.0805743041,
    "VarianceExplained": 0.0174479141
  },
  "a_comp_cor_06": {
    "CumulativeVarianceExplained": 0.2549571539,
    "Mask": "combined",
    "Method": "aCompCor",
    "Retained": true,
    "SingularValue": 60.4461538351,
    "VarianceExplained": 0.0150514419
  },
  "a_comp_cor_07": {
    "CumulativeVarianceExplained": 0.2695213085,
    "Mask": "combined",
    "Method": "aCompCor",
    "Retained": true,
    "SingularValue": 59.4596379217,
    "VarianceExplained": 0.0145641547
  },
  "a_comp_cor_08": {
    "CumulativeVarianceExplained": 0.2834993944,
    "Mask": "combined",
    "Method": "aCompCor",
    "Retained": true,
    "SingularValue": 58.2510116061,
    "VarianceExplained": 0.0139780859
  },
  "a_comp_cor_09": {
    "CumulativeVarianceExplained": 0.2960095346,
    "Mask": "combined",
    "Method": "aCompCor",
    "Retained": true,
    "SingularValue": 55.1074996631,
    "VarianceExplained": 0.0125101401
  },
  "a_comp_cor_10": {
    "CumulativeVarianceExplained": 0.3082243755,
    "Mask": "combined",
    "Method": "aCompCor",
    "Retained": true,
    "SingularValue": 54.4532149867,
    "VarianceExplained": 0.0122148409
  },
  "a_comp_cor_11": {
    "CumulativeVarianceExplained": 0.3192088191,
    "Mask": "combined",
    "Method": "aCompCor",
    "Retained": true,
    "SingularValue": 51.6379095169,
    "VarianceExplained": 0.0109844437
  },
  "a_comp_cor_12": {
    "CumulativeVarianceExplained": 0.329733269,
    "Mask": "combined",
    "Method": "aCompCor",
    "Retained": true,
    "SingularValue": 50.5451305006,
    "VarianceExplained": 0.0105244499
  },
  "a_comp_cor_13": {
    "CumulativeVarianceExplained": 0.3397588171,
    "Mask": "combined",
    "Method": "aCompCor",
    "Retained": true,
    "SingularValue": 49.332563112,
    "VarianceExplained": 0.010025548
  },
  "a_comp_cor_14": {
    "CumulativeVarianceExplained": 0.3490306526,
    "Mask": "combined",
    "Method": "aCompCor",
    "Retained": true,
    "SingularValue": 47.4419444047,
    "VarianceExplained": 0.0092718356
  },
  "a_comp_cor_15": {
    "CumulativeVarianceExplained": 0.3581508795,
    "Mask": "combined",
    "Method": "aCompCor",
    "Retained": true,
    "SingularValue": 47.052471559,
    "VarianceExplained": 0.0091202269
  },
  "a_comp_cor_16": {
    "CumulativeVarianceExplained": 0.3667002682,
    "Mask": "combined",
    "Method": "aCompCor",
    "Retained": true,
    "SingularValue": 45.5561642758,
    "VarianceExplained": 0.0085493887
  },
  "a_comp_cor_17": {
    "CumulativeVarianceExplained": 0.37455119,
    "Mask": "combined",
    "Method": "aCompCor",
    "Retained": true,
    "SingularValue": 43.655598321,
    "VarianceExplained": 0.0078509218
  },
  "a_comp_cor_18": {
    "CumulativeVarianceExplained": 0.3822854733,
    "Mask": "combined",
    "Method": "aCompCor",
    "Retained": true,
    "SingularValue": 43.3300966417,
    "VarianceExplained": 0.0077342833
  },
  "a_comp_cor_19": {
    "CumulativeVarianceExplained": 0.3899015615,
    "Mask": "combined",
    "Method": "aCompCor",
    "Retained": true,
    "SingularValue": 42.9977370654,
    "VarianceExplained": 0.0076160881
  },
  "a_comp_cor_20": {
    "CumulativeVarianceExplained": 0.3973263095,
    "Mask": "combined",
    "Method": "aCompCor",
    "Retained": true,
    "SingularValue": 42.4541821852,
    "VarianceExplained": 0.007424748
  },
  "a_comp_cor_21": {
    "CumulativeVarianceExplained": 0.4046182058,
    "Mask": "combined",
    "Method": "aCompCor",
    "Retained": true,
    "SingularValue": 42.0726494058,
    "VarianceExplained": 0.0072918963
  },
  "a_comp_cor_22": {
    "CumulativeVarianceExplained": 0.4117905408,
    "Mask": "combined",
    "Method": "aCompCor",
    "Retained": true,
    "SingularValue": 41.7263024286,
    "VarianceExplained": 0.007172335
  },
  "a_comp_cor_23": {
    "CumulativeVarianceExplained": 0.4187928978,
    "Mask": "combined",
    "Method": "aCompCor",
    "Retained": true,
    "SingularValue": 41.2288997032,
    "VarianceExplained": 0.007002357
  },
  "a_comp_cor_24": {
    "CumulativeVarianceExplained": 0.4256349734,
    "Mask": "combined",
    "Method": "aCompCor",
    "Retained": true,
    "SingularValue": 40.7543109252,
    "VarianceExplained": 0.0068420756
  },
  "a_comp_cor_25": {
    "CumulativeVarianceExplained": 0.4323473497,
    "Mask": "combined",
    "Method": "aCompCor",
    "Retained": true,
    "SingularValue": 40.3661904558,
    "VarianceExplained": 0.0067123762
  },
  "a_comp_cor_26": {
    "CumulativeVarianceExplained": 0.4388317486,
    "Mask": "combined",
    "Method": "aCompCor",
    "Retained": true,
    "SingularValue": 39.67477597,
    "VarianceExplained": 0.006484399
  },
  "a_comp_cor_27": {
    "CumulativeVarianceExplained": 0.445277015,
    "Mask": "combined",
    "Method": "aCompCor",
    "Retained": true,
    "SingularValue": 39.5548785429,
    "VarianceExplained": 0.0064452664
  },
  "a_comp_cor_28": {
    "CumulativeVarianceExplained": 0.451596796,
    "Mask": "combined",
    "Method": "aCompCor",
    "Retained": true,
    "SingularValue": 39.1679311191,
    "VarianceExplained": 0.006319781
  },
  "a_comp_cor_29": {
    "CumulativeVarianceExplained": 0.4578592708,
    "Mask": "combined",
    "Method": "aCompCor",
    "Retained": true,
    "SingularValue": 38.9899442908,
    "VarianceExplained": 0.0062624748
  },
  "a_comp_cor_30": {
    "CumulativeVarianceExplained": 0.4640110563,
    "Mask": "combined",
    "Method": "aCompCor",
    "Retained": true,
    "SingularValue": 38.6438343673,
    "VarianceExplained": 0.0061517855
  },
  "a_comp_cor_31": {
    "CumulativeVarianceExplained": 0.4700837638,
    "Mask": "combined",
    "Method": "aCompCor",
    "Retained": true,
    "SingularValue": 38.3946576854,
    "VarianceExplained": 0.0060727075
  },
  "a_comp_cor_32": {
    "CumulativeVarianceExplained": 0.47602713,
    "Mask": "combined",
    "Method": "aCompCor",
    "Retained": true,
    "SingularValue": 37.9835772503,
    "VarianceExplained": 0.0059433662
  },
  "a_comp_cor_33": {
    "CumulativeVarianceExplained": 0.4819635513,
    "Mask": "combined",
    "Method": "aCompCor",
    "Retained": true,
    "SingularValue": 37.9613787909,
    "VarianceExplained": 0.0059364213
  },
  "a_comp_cor_34": {
    "CumulativeVarianceExplained": 0.4877826624,
    "Mask": "combined",
    "Method": "aCompCor",
    "Retained": true,
    "SingularValue": 37.5844277973,
    "VarianceExplained": 0.0058191111
  },
  "a_comp_cor_35": {
    "CumulativeVarianceExplained": 0.4935385887,
    "Mask": "combined",
    "Method": "aCompCor",
    "Retained": true,
    "SingularValue": 37.3798222814,
    "VarianceExplained": 0.0057559263
  },
  "a_comp_cor_36": {
    "CumulativeVarianceExplained": 0.4992196126,
    "Mask": "combined",
    "Method": "aCompCor",
    "Retained": true,
    "SingularValue": 37.1358121524,
    "VarianceExplained": 0.0056810239
  },
  "a_comp_cor_37": {
    "CumulativeVarianceExplained": 0.5048247987,
    "Mask": "combined",
    "Method": "aCompCor",
    "Retained": true,
    "SingularValue": 36.8871105906,
    "VarianceExplained": 0.0056051861
  },
  "c_comp_cor_00": {
    "CumulativeVarianceExplained": 0.1133220712,
    "Mask": "CSF",
    "Method": "aCompCor",
    "Retained": true,
    "SingularValue": 60.6874559753,
    "VarianceExplained": 0.1133220712
  },
  "c_comp_cor_01": {
    "CumulativeVarianceExplained": 0.1989625286,
    "Mask": "CSF",
    "Method": "aCompCor",
    "Retained": true,
    "SingularValue": 52.7571309485,
    "VarianceExplained": 0.0856404574
  },
  "c_comp_cor_02": {
    "CumulativeVarianceExplained": 0.274179666,
    "Mask": "CSF",
    "Method": "aCompCor",
    "Retained": true,
    "SingularValue": 49.442461181,
    "VarianceExplained": 0.0752171375
  },
  "c_comp_cor_03": {
    "CumulativeVarianceExplained": 0.3375984647,
    "Mask": "CSF",
    "Method": "aCompCor",
    "Retained": true,
    "SingularValue": 45.3994598661,
    "VarianceExplained": 0.0634187987
  },
  "c_comp_cor_04": {
    "CumulativeVarianceExplained": 0.3931842056,
    "Mask": "CSF",
    "Method": "aCompCor",
    "Retained": true,
    "SingularValue": 42.5033713951,
    "VarianceExplained": 0.0555857409
  },
  "c_comp_cor_05": {
    "CumulativeVarianceExplained": 0.4427051486,
    "Mask": "CSF",
    "Method": "aCompCor",
    "Retained": true,
    "SingularValue": 40.117709883,
    "VarianceExplained": 0.049520943
  },
  "c_comp_cor_06": {
    "CumulativeVarianceExplained": 0.4855635893,
    "Mask": "CSF",
    "Method": "aCompCor",
    "Retained": true,
    "SingularValue": 37.3215664588,
    "VarianceExplained": 0.0428584407
  },
  "c_comp_cor_07": {
    "CumulativeVarianceExplained": 0.5147673261,
    "Mask": "CSF",
    "Method": "aCompCor",
    "Retained": true,
    "SingularValue": 30.8078146776,
    "VarianceExplained": 0.0292037368
  },
  "dropped_0": {
    "CumulativeVarianceExplained": 0.4986947464,
    "Mask": "Edge",
    "Method": "EdgeRegressor",
    "Retained": false,
    "SingularValue": 114.4925178503,
    "VarianceExplained": 0.0058822242
  },
  "dropped_1": {
    "CumulativeVarianceExplained": 0.5041976008,
    "Mask": "Edge",
    "Method": "EdgeRegressor",
    "Retained": false,
    "SingularValue": 110.7389320187,
    "VarianceExplained": 0.0055028544
  },
  "dropped_10": {
    "CumulativeVarianceExplained": 0.5481816969,
    "Mask": "Edge",
    "Method": "EdgeRegressor",
    "Retained": false,
    "SingularValue": 100.1594781516,
    "VarianceExplained": 0.0045016473
  },
  "dropped_100": {
    "CumulativeVarianceExplained": 0.7976788523,
    "Mask": "Edge",
    "Method": "EdgeRegressor",
    "Retained": false,
    "SingularValue": 68.5324642989,
    "VarianceExplained": 0.0021075605
  },
  "dropped_101": {
    "CumulativeVarianceExplained": 0.7997811542,
    "Mask": "Edge",
    "Method": "EdgeRegressor",
    "Retained": false,
    "SingularValue": 68.4469123198,
    "VarianceExplained": 0.0021023019
  },
  "dropped_102": {
    "CumulativeVarianceExplained": 0.8018773687,
    "Mask": "Edge",
    "Method": "EdgeRegressor",
    "Retained": false,
    "SingularValue": 68.3477420407,
    "VarianceExplained": 0.0020962144
  },
  "dropped_103": {
    "CumulativeVarianceExplained": 0.803965557,
    "Mask": "Edge",
    "Method": "EdgeRegressor",
    "Retained": false,
    "SingularValue": 68.2167703047,
    "VarianceExplained": 0.0020881884
  },
  "dropped_104": {
    "CumulativeVarianceExplained": 0.8060494199,
    "Mask": "Edge",
    "Method": "EdgeRegressor",
    "Retained": false,
    "SingularValue": 68.1460808538,
    "VarianceExplained": 0.0020838628
  },
  "dropped_105": {
    "CumulativeVarianceExplained": 0.8081186127,
    "Mask": "Edge",
    "Method": "EdgeRegressor",
    "Retained": false,
    "SingularValue": 67.9057898988,
    "VarianceExplained": 0.0020691929
  },
  "dropped_106": {
    "CumulativeVarianceExplained": 0.8101805409,
    "Mask": "Edge",
    "Method": "EdgeRegressor",
    "Retained": false,
    "SingularValue": 67.78647991,
    "VarianceExplained": 0.0020619281
  },
  "dropped_107": {
    "CumulativeVarianceExplained": 0.81223742,
    "Mask": "Edge",
    "Method": "EdgeRegressor",
    "Retained": false,
    "SingularValue": 67.7034348475,
    "VarianceExplained": 0.0020568791
  },
  "dropped_108": {
    "CumulativeVarianceExplained": 0.8142837945,
    "Mask": "Edge",
    "Method": "EdgeRegressor",
    "Retained": false,
    "SingularValue": 67.5303319751,
    "VarianceExplained": 0.0020463746
  },
  "dropped_109": {
    "CumulativeVarianceExplained": 0.8163252322,
    "Mask": "Edge",
    "Method": "EdgeRegressor",
    "Retained": false,
    "SingularValue": 67.448823193,
    "VarianceExplained": 0.0020414376
  },
  "dropped_11": {
    "CumulativeVarianceExplained": 0.5526204603,
    "Mask": "Edge",
    "Method": "EdgeRegressor",
    "Retained": false,
    "SingularValue": 99.4574491566,
    "VarianceExplained": 0.0044387634
  },
  "dropped_110": {
    "CumulativeVarianceExplained": 0.8183577004,
    "Mask": "Edge",
    "Method": "EdgeRegressor",
    "Retained": false,
    "SingularValue": 67.3004856006,
    "VarianceExplained": 0.0020324682
  },
  "dropped_111": {
    "CumulativeVarianceExplained": 0.8203845925,
    "Mask": "Edge",
    "Method": "EdgeRegressor",
    "Retained": false,
    "SingularValue": 67.2081027091,
    "VarianceExplained": 0.0020268921
  },
  "dropped_112": {
    "CumulativeVarianceExplained": 0.8224060418,
    "Mask": "Edge",
    "Method": "EdgeRegressor",
    "Retained": false,
    "SingularValue": 67.1178050711,
    "VarianceExplained": 0.0020214493
  },
  "dropped_113": {
    "CumulativeVarianceExplained": 0.8244104922,
    "Mask": "Edge",
    "Method": "EdgeRegressor",
    "Retained": false,
    "SingularValue": 66.8350037026,
    "VarianceExplained": 0.0020044504
  },
  "dropped_114": {
    "CumulativeVarianceExplained": 0.8264146727,
    "Mask": "Edge",
    "Method": "EdgeRegressor",
    "Retained": false,
    "SingularValue": 66.8305048653,
    "VarianceExplained": 0.0020041806
  },
  "dropped_115": {
    "CumulativeVarianceExplained": 0.8284130877,
    "Mask": "Edge",
    "Method": "EdgeRegressor",
    "Retained": false,
    "SingularValue": 66.7343073977,
    "VarianceExplained": 0.001998415
  },
  "dropped_116": {
    "CumulativeVarianceExplained": 0.8304029416,
    "Mask": "Edge",
    "Method": "EdgeRegressor",
    "Retained": false,
    "SingularValue": 66.5912113314,
    "VarianceExplained": 0.0019898539
  },
  "dropped_117": {
    "CumulativeVarianceExplained": 0.8323896652,
    "Mask": "Edge",
    "Method": "EdgeRegressor",
    "Retained": false,
    "SingularValue": 66.5388111318,
    "VarianceExplained": 0.0019867235
  },
  "dropped_118": {
    "CumulativeVarianceExplained": 0.8343699582,
    "Mask": "Edge",
    "Method": "EdgeRegressor",
    "Retained": false,
    "SingularValue": 66.4310401408,
    "VarianceExplained": 0.0019802931
  },
  "dropped_119": {
    "CumulativeVarianceExplained": 0.836341023,
    "Mask": "Edge",
    "Method": "EdgeRegressor",
    "Retained": false,
    "SingularValue": 66.2760734112,
    "VarianceExplained": 0.0019710648
  },
  "dropped_12": {
    "CumulativeVarianceExplained": 0.5568566034,
    "Mask": "Edge",
    "Method": "EdgeRegressor",
    "Retained": false,
    "SingularValue": 97.1609228998,
    "VarianceExplained": 0.0042361431
  },
  "dropped_120": {
    "CumulativeVarianceExplained": 0.8383046855,
    "Mask": "Edge",
    "Method": "EdgeRegressor",
    "Retained": false,
    "SingularValue": 66.1515073142,
    "VarianceExplained": 0.0019636625
  },
  "dropped_121": {
    "CumulativeVarianceExplained": 0.8402591885,
    "Mask": "Edge",
    "Method": "EdgeRegressor",
    "Retained": false,
    "SingularValue": 65.9970447304,
    "VarianceExplained": 0.001954503
  },
  "dropped_122": {
    "CumulativeVarianceExplained": 0.8422108613,
    "Mask": "Edge",
    "Method": "EdgeRegressor",
    "Retained": false,
    "SingularValue": 65.9492435502,
    "VarianceExplained": 0.0019516728
  },
  "dropped_123": {
    "CumulativeVarianceExplained": 0.8441596752,
    "Mask": "Edge",
    "Method": "EdgeRegressor",
    "Retained": false,
    "SingularValue": 65.9009247242,
    "VarianceExplained": 0.0019488139
  },
  "dropped_124": {
    "CumulativeVarianceExplained": 0.8460957288,
    "Mask": "Edge",
    "Method": "EdgeRegressor",
    "Retained": false,
    "SingularValue": 65.6848190618,
    "VarianceExplained": 0.0019360536
  },
  "dropped_125": {
    "CumulativeVarianceExplained": 0.8480246307,
    "Mask": "Edge",
    "Method": "EdgeRegressor",
    "Retained": false,
    "SingularValue": 65.5633870882,
    "VarianceExplained": 0.0019289018
  },
  "dropped_126": {
    "CumulativeVarianceExplained": 0.8499486197,
    "Mask": "Edge",
    "Method": "EdgeRegressor",
    "Retained": false,
    "SingularValue": 65.4798412763,
    "VarianceExplained": 0.0019239891
  },
  "dropped_127": {
    "CumulativeVarianceExplained": 0.8518690922,
    "Mask": "Edge",
    "Method": "EdgeRegressor",
    "Retained": false,
    "SingularValue": 65.4199735343,
    "VarianceExplained": 0.0019204725
  },
  "dropped_128": {
    "CumulativeVarianceExplained": 0.853782168,
    "Mask": "Edge",
    "Method": "EdgeRegressor",
    "Retained": false,
    "SingularValue": 65.2938691282,
    "VarianceExplained": 0.0019130758
  },
  "dropped_129": {
    "CumulativeVarianceExplained": 0.8556852483,
    "Mask": "Edge",
    "Method": "EdgeRegressor",
    "Retained": false,
    "SingularValue": 65.1230716159,
    "VarianceExplained": 0.0019030803
  },
  "dropped_13": {
    "CumulativeVarianceExplained": 0.5610366908,
    "Mask": "Edge",
    "Method": "EdgeRegressor",
    "Retained": false,
    "SingularValue": 96.5159299493,
    "VarianceExplained": 0.0041800874
  },
  "dropped_130": {
    "CumulativeVarianceExplained": 0.8575820462,
    "Mask": "Edge",
    "Method": "EdgeRegressor",
    "Retained": false,
    "SingularValue": 65.0154925447,
    "VarianceExplained": 0.001896798
  },
  "dropped_131": {
    "CumulativeVarianceExplained": 0.8594666581,
    "Mask": "Edge",
    "Method": "EdgeRegressor",
    "Retained": false,
    "SingularValue": 64.8063073846,
    "VarianceExplained": 0.0018846118
  },
  "dropped_132": {
    "CumulativeVarianceExplained": 0.8613457747,
    "Mask": "Edge",
    "Method": "EdgeRegressor",
    "Retained": false,
    "SingularValue": 64.7117570773,
    "VarianceExplained": 0.0018791167
  },
  "dropped_133": {
    "CumulativeVarianceExplained": 0.8632221522,
    "Mask": "Edge",
    "Method": "EdgeRegressor",
    "Retained": false,
    "SingularValue": 64.6645748581,
    "VarianceExplained": 0.0018763775
  },
  "dropped_134": {
    "CumulativeVarianceExplained": 0.8650901937,
    "Mask": "Edge",
    "Method": "EdgeRegressor",
    "Retained": false,
    "SingularValue": 64.5207749675,
    "VarianceExplained": 0.0018680415
  },
  "dropped_135": {
    "CumulativeVarianceExplained": 0.8669560518,
    "Mask": "Edge",
    "Method": "EdgeRegressor",
    "Retained": false,
    "SingularValue": 64.4830584986,
    "VarianceExplained": 0.0018658581
  },
  "dropped_136": {
    "CumulativeVarianceExplained": 0.8688071509,
    "Mask": "Edge",
    "Method": "EdgeRegressor",
    "Retained": false,
    "SingularValue": 64.2275204643,
    "VarianceExplained": 0.0018510991
  },
  "dropped_137": {
    "CumulativeVarianceExplained": 0.8706519689,
    "Mask": "Edge",
    "Method": "EdgeRegressor",
    "Retained": false,
    "SingularValue": 64.118458742,
    "VarianceExplained": 0.0018448179
  },
  "dropped_138": {
    "CumulativeVarianceExplained": 0.8724866646,
    "Mask": "Edge",
    "Method": "EdgeRegressor",
    "Retained": false,
    "SingularValue": 63.9423129882,
    "VarianceExplained": 0.0018346957
  },
  "dropped_139": {
    "CumulativeVarianceExplained": 0.8743189065,
    "Mask": "Edge",
    "Method": "EdgeRegressor",
    "Retained": false,
    "SingularValue": 63.8995398546,
    "VarianceExplained": 0.001832242
  },
  "dropped_14": {
    "CumulativeVarianceExplained": 0.5651025552,
    "Mask": "Edge",
    "Method": "EdgeRegressor",
    "Retained": false,
    "SingularValue": 95.1881228323,
    "VarianceExplained": 0.0040658644
  },
  "dropped_140": {
    "CumulativeVarianceExplained": 0.8761401155,
    "Mask": "Edge",
    "Method": "EdgeRegressor",
    "Retained": false,
    "SingularValue": 63.7068616663,
    "VarianceExplained": 0.001821209
  },
  "dropped_141": {
    "CumulativeVarianceExplained": 0.8779595314,
    "Mask": "Edge",
    "Method": "EdgeRegressor",
    "Retained": false,
    "SingularValue": 63.6754925356,
    "VarianceExplained": 0.0018194159
  },
  "dropped_142": {
    "CumulativeVarianceExplained": 0.8797712957,
    "Mask": "Edge",
    "Method": "EdgeRegressor",
    "Retained": false,
    "SingularValue": 63.5414559184,
    "VarianceExplained": 0.0018117642
  },
  "dropped_143": {
    "CumulativeVarianceExplained": 0.8815787378,
    "Mask": "Edge",
    "Method": "EdgeRegressor",
    "Retained": false,
    "SingularValue": 63.4656180627,
    "VarianceExplained": 0.0018074421
  },
  "dropped_144": {
    "CumulativeVarianceExplained": 0.8833780748,
    "Mask": "Edge",
    "Method": "EdgeRegressor",
    "Retained": false,
    "SingularValue": 63.3231598434,
    "VarianceExplained": 0.001799337
  },
  "dropped_145": {
    "CumulativeVarianceExplained": 0.8851699935,
    "Mask": "Edge",
    "Method": "EdgeRegressor",
    "Retained": false,
    "SingularValue": 63.1924909092,
    "VarianceExplained": 0.0017919187
  },
  "dropped_146": {
    "CumulativeVarianceExplained": 0.8869583818,
    "Mask": "Edge",
    "Method": "EdgeRegressor",
    "Retained": false,
    "SingularValue": 63.1302082999,
    "VarianceExplained": 0.0017883882
  },
  "dropped_147": {
    "CumulativeVarianceExplained": 0.8887416691,
    "Mask": "Edge",
    "Method": "EdgeRegressor",
    "Retained": false,
    "SingularValue": 63.0401129037,
    "VarianceExplained": 0.0017832873
  },
  "dropped_148": {
    "CumulativeVarianceExplained": 0.8905149346,
    "Mask": "Edge",
    "Method": "EdgeRegressor",
    "Retained": false,
    "SingularValue": 62.8627247064,
    "VarianceExplained": 0.0017732655
  },
  "dropped_149": {
    "CumulativeVarianceExplained": 0.8922819958,
    "Mask": "Edge",
    "Method": "EdgeRegressor",
    "Retained": false,
    "SingularValue": 62.7526561334,
    "VarianceExplained": 0.0017670612
  },
  "dropped_15": {
    "CumulativeVarianceExplained": 0.5691278281,
    "Mask": "Edge",
    "Method": "EdgeRegressor",
    "Retained": false,
    "SingularValue": 94.7117770284,
    "VarianceExplained": 0.0040252729
  },
  "dropped_150": {
    "CumulativeVarianceExplained": 0.8940443866,
    "Mask": "Edge",
    "Method": "EdgeRegressor",
    "Retained": false,
    "SingularValue": 62.6696724792,
    "VarianceExplained": 0.0017623908
  },
  "dropped_151": {
    "CumulativeVarianceExplained": 0.8957987762,
    "Mask": "Edge",
    "Method": "EdgeRegressor",
    "Retained": false,
    "SingularValue": 62.5272529412,
    "VarianceExplained": 0.0017543897
  },
  "dropped_152": {
    "CumulativeVarianceExplained": 0.897549266,
    "Mask": "Edge",
    "Method": "EdgeRegressor",
    "Retained": false,
    "SingularValue": 62.4577174684,
    "VarianceExplained": 0.0017504898
  },
  "dropped_153": {
    "CumulativeVarianceExplained": 0.8992944934,
    "Mask": "Edge",
    "Method": "EdgeRegressor",
    "Retained": false,
    "SingularValue": 62.3637655321,
    "VarianceExplained": 0.0017452274
  },
  "dropped_154": {
    "CumulativeVarianceExplained": 0.9010344755,
    "Mask": "Edge",
    "Method": "EdgeRegressor",
    "Retained": false,
    "SingularValue": 62.2699773152,
    "VarianceExplained": 0.0017399821
  },
  "dropped_155": {
    "CumulativeVarianceExplained": 0.9027684664,
    "Mask": "Edge",
    "Method": "EdgeRegressor",
    "Retained": false,
    "SingularValue": 62.1626805393,
    "VarianceExplained": 0.001733991
  },
  "dropped_156": {
    "CumulativeVarianceExplained": 0.9044970585,
    "Mask": "Edge",
    "Method": "EdgeRegressor",
    "Retained": false,
    "SingularValue": 62.0658307954,
    "VarianceExplained": 0.001728592
  },
  "dropped_157": {
    "CumulativeVarianceExplained": 0.9062115841,
    "Mask": "Edge",
    "Method": "EdgeRegressor",
    "Retained": false,
    "SingularValue": 61.8127839925,
    "VarianceExplained": 0.0017145256
  },
  "dropped_158": {
    "CumulativeVarianceExplained": 0.9079205507,
    "Mask": "Edge",
    "Method": "EdgeRegressor",
    "Retained": false,
    "SingularValue": 61.7124957067,
    "VarianceExplained": 0.0017089666
  },
  "dropped_159": {
    "CumulativeVarianceExplained": 0.9096181243,
    "Mask": "Edge",
    "Method": "EdgeRegressor",
    "Retained": false,
    "SingularValue": 61.5064457998,
    "VarianceExplained": 0.0016975736
  },
  "dropped_16": {
    "CumulativeVarianceExplained": 0.5730410167,
    "Mask": "Edge",
    "Method": "EdgeRegressor",
    "Retained": false,
    "SingularValue": 93.3838363095,
    "VarianceExplained": 0.0039131886
  },
  "dropped_160": {
    "CumulativeVarianceExplained": 0.9113122001,
    "Mask": "Edge",
    "Method": "EdgeRegressor",
    "Retained": false,
    "SingularValue": 61.4430447718,
    "VarianceExplained": 0.0016940757
  },
  "dropped_161": {
    "CumulativeVarianceExplained": 0.9130019307,
    "Mask": "Edge",
    "Method": "EdgeRegressor",
    "Retained": false,
    "SingularValue": 61.364197154,
    "VarianceExplained": 0.0016897306
  },
  "dropped_162": {
    "CumulativeVarianceExplained": 0.914685871,
    "Mask": "Edge",
    "Method": "EdgeRegressor",
    "Retained": false,
    "SingularValue": 61.2589662594,
    "VarianceExplained": 0.0016839403
  },
  "dropped_163": {
    "CumulativeVarianceExplained": 0.9163647032,
    "Mask": "Edge",
    "Method": "EdgeRegressor",
    "Retained": false,
    "SingularValue": 61.1659840497,
    "VarianceExplained": 0.0016788322
  },
  "dropped_164": {
    "CumulativeVarianceExplained": 0.9180372092,
    "Mask": "Edge",
    "Method": "EdgeRegressor",
    "Retained": false,
    "SingularValue": 61.0506316968,
    "VarianceExplained": 0.001672506
  },
  "dropped_165": {
    "CumulativeVarianceExplained": 0.9197044681,
    "Mask": "Edge",
    "Method": "EdgeRegressor",
    "Retained": false,
    "SingularValue": 60.9547908777,
    "VarianceExplained": 0.0016672589
  },
  "dropped_166": {
    "CumulativeVarianceExplained": 0.9213649615,
    "Mask": "Edge",
    "Method": "EdgeRegressor",
    "Retained": false,
    "SingularValue": 60.8309911732,
    "VarianceExplained": 0.0016604934
  },
  "dropped_167": {
    "CumulativeVarianceExplained": 0.9230226103,
    "Mask": "Edge",
    "Method": "EdgeRegressor",
    "Retained": false,
    "SingularValue": 60.778863892,
    "VarianceExplained": 0.0016576488
  },
  "dropped_168": {
    "CumulativeVarianceExplained": 0.9246734233,
    "Mask": "Edge",
    "Method": "EdgeRegressor",
    "Retained": false,
    "SingularValue": 60.6534157479,
    "VarianceExplained": 0.001650813
  },
  "dropped_169": {
    "CumulativeVarianceExplained": 0.9263185614,
    "Mask": "Edge",
    "Method": "EdgeRegressor",
    "Retained": false,
    "SingularValue": 60.549073179,
    "VarianceExplained": 0.0016451381
  },
  "dropped_17": {
    "CumulativeVarianceExplained": 0.5768671103,
    "Mask": "Edge",
    "Method": "EdgeRegressor",
    "Retained": false,
    "SingularValue": 92.3387761938,
    "VarianceExplained": 0.0038260936
  },
  "dropped_170": {
    "CumulativeVarianceExplained": 0.9279557906,
    "Mask": "Edge",
    "Method": "EdgeRegressor",
    "Retained": false,
    "SingularValue": 60.403353892,
    "VarianceExplained": 0.0016372292
  },
  "dropped_171": {
    "CumulativeVarianceExplained": 0.9295895666,
    "Mask": "Edge",
    "Method": "EdgeRegressor",
    "Retained": false,
    "SingularValue": 60.3396204406,
    "VarianceExplained": 0.001633776
  },
  "dropped_172": {
    "CumulativeVarianceExplained": 0.9312151928,
    "Mask": "Edge",
    "Method": "EdgeRegressor",
    "Retained": false,
    "SingularValue": 60.1889371057,
    "VarianceExplained": 0.0016256263
  },
  "dropped_173": {
    "CumulativeVarianceExplained": 0.932837025,
    "Mask": "Edge",
    "Method": "EdgeRegressor",
    "Retained": false,
    "SingularValue": 60.1186572608,
    "VarianceExplained": 0.0016218322
  },
  "dropped_174": {
    "CumulativeVarianceExplained": 0.9344569683,
    "Mask": "Edge",
    "Method": "EdgeRegressor",
    "Retained": false,
    "SingularValue": 60.0836384572,
    "VarianceExplained": 0.0016199433
  },
  "dropped_175": {
    "CumulativeVarianceExplained": 0.9360689555,
    "Mask": "Edge",
    "Method": "EdgeRegressor",
    "Retained": false,
    "SingularValue": 59.9359117905,
    "VarianceExplained": 0.0016119872
  },
  "dropped_176": {
    "CumulativeVarianceExplained": 0.9376749921,
    "Mask": "Edge",
    "Method": "EdgeRegressor",
    "Retained": false,
    "SingularValue": 59.8251842581,
    "VarianceExplained": 0.0016060366
  },
  "dropped_177": {
    "CumulativeVarianceExplained": 0.939274091,
    "Mask": "Edge",
    "Method": "EdgeRegressor",
    "Retained": false,
    "SingularValue": 59.6958278172,
    "VarianceExplained": 0.0015990989
  },
  "dropped_178": {
    "CumulativeVarianceExplained": 0.9408628239,
    "Mask": "Edge",
    "Method": "EdgeRegressor",
    "Retained": false,
    "SingularValue": 59.5020278865,
    "VarianceExplained": 0.0015887329
  },
  "dropped_179": {
    "CumulativeVarianceExplained": 0.9424492172,
    "Mask": "Edge",
    "Method": "EdgeRegressor",
    "Retained": false,
    "SingularValue": 59.4581982967,
    "VarianceExplained": 0.0015863932
  },
  "dropped_18": {
    "CumulativeVarianceExplained": 0.5806421068,
    "Mask": "Edge",
    "Method": "EdgeRegressor",
    "Retained": false,
    "SingularValue": 91.7201157007,
    "VarianceExplained": 0.0037749965
  },
  "dropped_180": {
    "CumulativeVarianceExplained": 0.9440258791,
    "Mask": "Edge",
    "Method": "EdgeRegressor",
    "Retained": false,
    "SingularValue": 59.2755511398,
    "VarianceExplained": 0.0015766619
  },
  "dropped_181": {
    "CumulativeVarianceExplained": 0.9455977479,
    "Mask": "Edge",
    "Method": "EdgeRegressor",
    "Retained": false,
    "SingularValue": 59.1853834291,
    "VarianceExplained": 0.0015718688
  },
  "dropped_182": {
    "CumulativeVarianceExplained": 0.9471665045,
    "Mask": "Edge",
    "Method": "EdgeRegressor",
    "Retained": false,
    "SingularValue": 59.1267641173,
    "VarianceExplained": 0.0015687567
  },
  "dropped_183": {
    "CumulativeVarianceExplained": 0.9487222399,
    "Mask": "Edge",
    "Method": "EdgeRegressor",
    "Retained": false,
    "SingularValue": 58.8808644975,
    "VarianceExplained": 0.0015557353
  },
  "dropped_184": {
    "CumulativeVarianceExplained": 0.9502747477,
    "Mask": "Edge",
    "Method": "EdgeRegressor",
    "Retained": false,
    "SingularValue": 58.8197567701,
    "VarianceExplained": 0.0015525079
  },
  "dropped_185": {
    "CumulativeVarianceExplained": 0.9518197545,
    "Mask": "Edge",
    "Method": "EdgeRegressor",
    "Retained": false,
    "SingularValue": 58.6774885539,
    "VarianceExplained": 0.0015450068
  },
  "dropped_186": {
    "CumulativeVarianceExplained": 0.9533613403,
    "Mask": "Edge",
    "Method": "EdgeRegressor",
    "Retained": false,
    "SingularValue": 58.6124888711,
    "VarianceExplained": 0.0015415858
  },
  "dropped_187": {
    "CumulativeVarianceExplained": 0.9548945696,
    "Mask": "Edge",
    "Method": "EdgeRegressor",
    "Retained": false,
    "SingularValue": 58.4534126279,
    "VarianceExplained": 0.0015332293
  },
  "dropped_188": {
    "CumulativeVarianceExplained": 0.9564251552,
    "Mask": "Edge",
    "Method": "EdgeRegressor",
    "Retained": false,
    "SingularValue": 58.4029970951,
    "VarianceExplained": 0.0015305856
  },
  "dropped_189": {
    "CumulativeVarianceExplained": 0.9579481197,
    "Mask": "Edge",
    "Method": "EdgeRegressor",
    "Retained": false,
    "SingularValue": 58.2574142202,
    "VarianceExplained": 0.0015229645
  },
  "dropped_19": {
    "CumulativeVarianceExplained": 0.5843374786,
    "Mask": "Edge",
    "Method": "EdgeRegressor",
    "Retained": false,
    "SingularValue": 90.7476500743,
    "VarianceExplained": 0.0036953718
  },
  "dropped_190": {
    "CumulativeVarianceExplained": 0.9594671764,
    "Mask": "Edge",
    "Method": "EdgeRegressor",
    "Retained": false,
    "SingularValue": 58.1826250012,
    "VarianceExplained": 0.0015190567
  },
  "dropped_191": {
    "CumulativeVarianceExplained": 0.9609781408,
    "Mask": "Edge",
    "Method": "EdgeRegressor",
    "Retained": false,
    "SingularValue": 58.0274441297,
    "VarianceExplained": 0.0015109644
  },
  "dropped_192": {
    "CumulativeVarianceExplained": 0.9624826385,
    "Mask": "Edge",
    "Method": "EdgeRegressor",
    "Retained": false,
    "SingularValue": 57.9031365016,
    "VarianceExplained": 0.0015044977
  },
  "dropped_193": {
    "CumulativeVarianceExplained": 0.963977596,
    "Mask": "Edge",
    "Method": "EdgeRegressor",
    "Retained": false,
    "SingularValue": 57.7192577444,
    "VarianceExplained": 0.0014949575
  },
  "dropped_194": {
    "CumulativeVarianceExplained": 0.9654662621,
    "Mask": "Edge",
    "Method": "EdgeRegressor",
    "Retained": false,
    "SingularValue": 57.5976767416,
    "VarianceExplained": 0.0014886661
  },
  "dropped_195": {
    "CumulativeVarianceExplained": 0.9669448122,
    "Mask": "Edge",
    "Method": "EdgeRegressor",
    "Retained": false,
    "SingularValue": 57.4016449089,
    "VarianceExplained": 0.0014785501
  },
  "dropped_196": {
    "CumulativeVarianceExplained": 0.9684204915,
    "Mask": "Edge",
    "Method": "EdgeRegressor",
    "Retained": false,
    "SingularValue": 57.3458932345,
    "VarianceExplained": 0.0014756794
  },
  "dropped_197": {
    "CumulativeVarianceExplained": 0.9698915967,
    "Mask": "Edge",
    "Method": "EdgeRegressor",
    "Retained": false,
    "SingularValue": 57.2569464072,
    "VarianceExplained": 0.0014711052
  },
  "dropped_198": {
    "CumulativeVarianceExplained": 0.9713516742,
    "Mask": "Edge",
    "Method": "EdgeRegressor",
    "Retained": false,
    "SingularValue": 57.0419371511,
    "VarianceExplained": 0.0014600774
  },
  "dropped_199": {
    "CumulativeVarianceExplained": 0.9728048374,
    "Mask": "Edge",
    "Method": "EdgeRegressor",
    "Retained": false,
    "SingularValue": 56.9067152778,
    "VarianceExplained": 0.0014531632
  },
  "dropped_2": {
    "CumulativeVarianceExplained": 0.509621755,
    "Mask": "Edge",
    "Method": "EdgeRegressor",
    "Retained": false,
    "SingularValue": 109.9442020766,
    "VarianceExplained": 0.0054241542
  },
  "dropped_20": {
    "CumulativeVarianceExplained": 0.58799309,
    "Mask": "Edge",
    "Method": "EdgeRegressor",
    "Retained": false,
    "SingularValue": 90.2581301368,
    "VarianceExplained": 0.0036556114
  },
  "dropped_200": {
    "CumulativeVarianceExplained": 0.9742504771,
    "Mask": "Edge",
    "Method": "EdgeRegressor",
    "Retained": false,
    "SingularValue": 56.7592108611,
    "VarianceExplained": 0.0014456397
  },
  "dropped_201": {
    "CumulativeVarianceExplained": 0.9756929233,
    "Mask": "Edge",
    "Method": "EdgeRegressor",
    "Retained": false,
    "SingularValue": 56.6964859126,
    "VarianceExplained": 0.0014424463
  },
  "dropped_202": {
    "CumulativeVarianceExplained": 0.9771279752,
    "Mask": "Edge",
    "Method": "EdgeRegressor",
    "Retained": false,
    "SingularValue": 56.5509773796,
    "VarianceExplained": 0.0014350518
  },
  "dropped_203": {
    "CumulativeVarianceExplained": 0.9785547144,
    "Mask": "Edge",
    "Method": "EdgeRegressor",
    "Retained": false,
    "SingularValue": 56.386951154,
    "VarianceExplained": 0.0014267392
  },
  "dropped_204": {
    "CumulativeVarianceExplained": 0.979974805,
    "Mask": "Edge",
    "Method": "EdgeRegressor",
    "Retained": false,
    "SingularValue": 56.255418234,
    "VarianceExplained": 0.0014200907
  },
  "dropped_205": {
    "CumulativeVarianceExplained": 0.9813875145,
    "Mask": "Edge",
    "Method": "EdgeRegressor",
    "Retained": false,
    "SingularValue": 56.1090282664,
    "VarianceExplained": 0.0014127095
  },
  "dropped_206": {
    "CumulativeVarianceExplained": 0.9827925791,
    "Mask": "Edge",
    "Method": "EdgeRegressor",
    "Retained": false,
    "SingularValue": 55.9570048254,
    "VarianceExplained": 0.0014050646
  },
  "dropped_207": {
    "CumulativeVarianceExplained": 0.9841925045,
    "Mask": "Edge",
    "Method": "EdgeRegressor",
    "Retained": false,
    "SingularValue": 55.8545779107,
    "VarianceExplained": 0.0013999255
  },
  "dropped_208": {
    "CumulativeVarianceExplained": 0.9855903411,
    "Mask": "Edge",
    "Method": "EdgeRegressor",
    "Retained": false,
    "SingularValue": 55.8128909854,
    "VarianceExplained": 0.0013978366
  },
  "dropped_209": {
    "CumulativeVarianceExplained": 0.9869789776,
    "Mask": "Edge",
    "Method": "EdgeRegressor",
    "Retained": false,
    "SingularValue": 55.6289174919,
    "VarianceExplained": 0.0013886365
  },
  "dropped_21": {
    "CumulativeVarianceExplained": 0.5916022669,
    "Mask": "Edge",
    "Method": "EdgeRegressor",
    "Retained": false,
    "SingularValue": 89.6830572535,
    "VarianceExplained": 0.0036091769
  },
  "dropped_210": {
    "CumulativeVarianceExplained": 0.9883493742,
    "Mask": "Edge",
    "Method": "EdgeRegressor",
    "Retained": false,
    "SingularValue": 55.2623626327,
    "VarianceExplained": 0.0013703966
  },
  "dropped_211": {
    "CumulativeVarianceExplained": 0.9897139444,
    "Mask": "Edge",
    "Method": "EdgeRegressor",
    "Retained": false,
    "SingularValue": 55.1447617608,
    "VarianceExplained": 0.0013645702
  },
  "dropped_212": {
    "CumulativeVarianceExplained": 0.9910708306,
    "Mask": "Edge",
    "Method": "EdgeRegressor",
    "Retained": false,
    "SingularValue": 54.9892804659,
    "VarianceExplained": 0.0013568862
  },
  "dropped_213": {
    "CumulativeVarianceExplained": 0.9924128924,
    "Mask": "Edge",
    "Method": "EdgeRegressor",
    "Retained": false,
    "SingularValue": 54.6880657274,
    "VarianceExplained": 0.0013420617
  },
  "dropped_214": {
    "CumulativeVarianceExplained": 0.9937378003,
    "Mask": "Edge",
    "Method": "EdgeRegressor",
    "Retained": false,
    "SingularValue": 54.3374404364,
    "VarianceExplained": 0.001324908
  },
  "dropped_215": {
    "CumulativeVarianceExplained": 0.9950621979,
    "Mask": "Edge",
    "Method": "EdgeRegressor",
    "Retained": false,
    "SingularValue": 54.3269727668,
    "VarianceExplained": 0.0013243976
  },
  "dropped_216": {
    "CumulativeVarianceExplained": 0.996379614,
    "Mask": "Edge",
    "Method": "EdgeRegressor",
    "Retained": false,
    "SingularValue": 54.1835932132,
    "VarianceExplained": 0.0013174161
  },
  "dropped_217": {
    "CumulativeVarianceExplained": 0.9976796547,
    "Mask": "Edge",
    "Method": "EdgeRegressor",
    "Retained": false,
    "SingularValue": 53.825094489,
    "VarianceExplained": 0.0013000407
  },
  "dropped_218": {
    "CumulativeVarianceExplained": 0.99896817,
    "Mask": "Edge",
    "Method": "EdgeRegressor",
    "Retained": false,
    "SingularValue": 53.5859698724,
    "VarianceExplained": 0.0012885152
  },
  "dropped_219": {
    "CumulativeVarianceExplained": 1.0,
    "Mask": "Edge",
    "Method": "EdgeRegressor",
    "Retained": false,
    "SingularValue": 47.9524061566,
    "VarianceExplained": 0.00103183
  },
  "dropped_22": {
    "CumulativeVarianceExplained": 0.5951475763,
    "Mask": "Edge",
    "Method": "EdgeRegressor",
    "Retained": false,
    "SingularValue": 88.88600552,
    "VarianceExplained": 0.0035453094
  },
  "dropped_220": {
    "CumulativeVarianceExplained": 1.0,
    "Mask": "Edge",
    "Method": "EdgeRegressor",
    "Retained": false,
    "SingularValue": 0.0,
    "VarianceExplained": 0.0
  },
  "dropped_221": {
    "CumulativeVarianceExplained": 1.0,
    "Mask": "Edge",
    "Method": "EdgeRegressor",
    "Retained": false,
    "SingularValue": 0.0,
    "VarianceExplained": 0.0
  },
  "dropped_222": {
    "CumulativeVarianceExplained": 1.0,
    "Mask": "Edge",
    "Method": "EdgeRegressor",
    "Retained": false,
    "SingularValue": 0.0,
    "VarianceExplained": 0.0
  },
  "dropped_223": {
    "CumulativeVarianceExplained": 1.0,
    "Mask": "Edge",
    "Method": "EdgeRegressor",
    "Retained": false,
    "SingularValue": 0.0,
    "VarianceExplained": 0.0
  },
  "dropped_224": {
    "CumulativeVarianceExplained": 1.0,
    "Mask": "Edge",
    "Method": "EdgeRegressor",
    "Retained": false,
    "SingularValue": 0.0,
    "VarianceExplained": 0.0
  },
  "dropped_225": {
    "CumulativeVarianceExplained": 1.0,
    "Mask": "Edge",
    "Method": "EdgeRegressor",
    "Retained": false,
    "SingularValue": 0.0,
    "VarianceExplained": 0.0
  },
  "dropped_23": {
    "CumulativeVarianceExplained": 0.5986619068,
    "Mask": "Edge",
    "Method": "EdgeRegressor",
    "Retained": false,
    "SingularValue": 88.496810907,
    "VarianceExplained": 0.0035143305
  },
  "dropped_24": {
    "CumulativeVarianceExplained": 0.6021457406,
    "Mask": "Edge",
    "Method": "EdgeRegressor",
    "Retained": false,
    "SingularValue": 88.1119940925,
    "VarianceExplained": 0.0034838337
  },
  "dropped_25": {
    "CumulativeVarianceExplained": 0.6055305043,
    "Mask": "Edge",
    "Method": "EdgeRegressor",
    "Retained": false,
    "SingularValue": 86.8501351346,
    "VarianceExplained": 0.0033847637
  },
  "dropped_26": {
    "CumulativeVarianceExplained": 0.6089025847,
    "Mask": "Edge",
    "Method": "EdgeRegressor",
    "Retained": false,
    "SingularValue": 86.6872607575,
    "VarianceExplained": 0.0033720804
  },
  "dropped_27": {
    "CumulativeVarianceExplained": 0.6121807918,
    "Mask": "Edge",
    "Method": "EdgeRegressor",
    "Retained": false,
    "SingularValue": 85.4721268512,
    "VarianceExplained": 0.0032782071
  },
  "dropped_28": {
    "CumulativeVarianceExplained": 0.615457802,
    "Mask": "Edge",
    "Method": "EdgeRegressor",
    "Retained": false,
    "SingularValue": 85.4565228524,
    "VarianceExplained": 0.0032770102
  },
  "dropped_29": {
    "CumulativeVarianceExplained": 0.6186939242,
    "Mask": "Edge",
    "Method": "EdgeRegressor",
    "Retained": false,
    "SingularValue": 84.9217187335,
    "VarianceExplained": 0.0032361222
  },
  "dropped_3": {
    "CumulativeVarianceExplained": 0.514954057,
    "Mask": "Edge",
    "Method": "EdgeRegressor",
    "Retained": false,
    "SingularValue": 109.0093345892,
    "VarianceExplained": 0.005332302
  },
  "dropped_30": {
    "CumulativeVarianceExplained": 0.621896651,
    "Mask": "Edge",
    "Method": "EdgeRegressor",
    "Retained": false,
    "SingularValue": 84.4824048072,
    "VarianceExplained": 0.0032027268
  },
  "dropped_31": {
    "CumulativeVarianceExplained": 0.6250450075,
    "Mask": "Edge",
    "Method": "EdgeRegressor",
    "Retained": false,
    "SingularValue": 83.7622369881,
    "VarianceExplained": 0.0031483564
  },
  "dropped_32": {
    "CumulativeVarianceExplained": 0.6281567735,
    "Mask": "Edge",
    "Method": "EdgeRegressor",
    "Retained": false,
    "SingularValue": 83.2740689007,
    "VarianceExplained": 0.003111766
  },
  "dropped_33": {
    "CumulativeVarianceExplained": 0.631231554,
    "Mask": "Edge",
    "Method": "EdgeRegressor",
    "Retained": false,
    "SingularValue": 82.7777046406,
    "VarianceExplained": 0.0030747805
  },
  "dropped_34": {
    "CumulativeVarianceExplained": 0.634275327,
    "Mask": "Edge",
    "Method": "EdgeRegressor",
    "Retained": false,
    "SingularValue": 82.3592622063,
    "VarianceExplained": 0.003043773
  },
  "dropped_35": {
    "CumulativeVarianceExplained": 0.6372838797,
    "Mask": "Edge",
    "Method": "EdgeRegressor",
    "Retained": false,
    "SingularValue": 81.8813758193,
    "VarianceExplained": 0.0030085527
  },
  "dropped_36": {
    "CumulativeVarianceExplained": 0.64028441,
    "Mask": "Edge",
    "Method": "EdgeRegressor",
    "Retained": false,
    "SingularValue": 81.7721334419,
    "VarianceExplained": 0.0030005303
  },
  "dropped_37": {
    "CumulativeVarianceExplained": 0.6432512131,
    "Mask": "Edge",
    "Method": "EdgeRegressor",
    "Retained": false,
    "SingularValue": 81.3112575906,
    "VarianceExplained": 0.0029668031
  },
  "dropped_38": {
    "CumulativeVarianceExplained": 0.6462057637,
    "Mask": "Edge",
    "Method": "EdgeRegressor",
    "Retained": false,
    "SingularValue": 81.1431832654,
    "VarianceExplained": 0.0029545507
  },
  "dropped_39": {
    "CumulativeVarianceExplained": 0.6491325607,
    "Mask": "Edge",
    "Method": "EdgeRegressor",
    "Retained": false,
    "SingularValue": 80.7611726477,
    "VarianceExplained": 0.002926797
  },
  "dropped_4": {
    "CumulativeVarianceExplained": 0.5200397604,
    "Mask": "Edge",
    "Method": "EdgeRegressor",
    "Retained": false,
    "SingularValue": 106.4588654091,
    "VarianceExplained": 0.0050857034
  },
  "dropped_40": {
    "CumulativeVarianceExplained": 0.6520361961,
    "Mask": "Edge",
    "Method": "EdgeRegressor",
    "Retained": false,
    "SingularValue": 80.4409819466,
    "VarianceExplained": 0.0029036354
  },
  "dropped_41": {
    "CumulativeVarianceExplained": 0.6549085554,
    "Mask": "Edge",
    "Method": "EdgeRegressor",
    "Retained": false,
    "SingularValue": 80.0065783601,
    "VarianceExplained": 0.0028723592
  },
  "dropped_42": {
    "CumulativeVarianceExplained": 0.6577632715,
    "Mask": "Edge",
    "Method": "EdgeRegressor",
    "Retained": false,
    "SingularValue": 79.7604840283,
    "VarianceExplained": 0.0028547161
  },
  "dropped_43": {
    "CumulativeVarianceExplained": 0.6605829443,
    "Mask": "Edge",
    "Method": "EdgeRegressor",
    "Retained": false,
    "SingularValue": 79.2694192739,
    "VarianceExplained": 0.0028196728
  },
  "dropped_44": {
    "CumulativeVarianceExplained": 0.6633880957,
    "Mask": "Edge",
    "Method": "EdgeRegressor",
    "Retained": false,
    "SingularValue": 79.0650358905,
    "VarianceExplained": 0.0028051514
  },
  "dropped_45": {
    "CumulativeVarianceExplained": 0.6661689787,
    "Mask": "Edge",
    "Method": "EdgeRegressor",
    "Retained": false,
    "SingularValue": 78.7222829042,
    "VarianceExplained": 0.002780883
  },
  "dropped_46": {
    "CumulativeVarianceExplained": 0.6689363112,
    "Mask": "Edge",
    "Method": "EdgeRegressor",
    "Retained": false,
    "SingularValue": 78.5302523897,
    "VarianceExplained": 0.0027673325
  },
  "dropped_47": {
    "CumulativeVarianceExplained": 0.671669359,
    "Mask": "Edge",
    "Method": "EdgeRegressor",
    "Retained": false,
    "SingularValue": 78.0422768776,
    "VarianceExplained": 0.0027330478
  },
  "dropped_48": {
    "CumulativeVarianceExplained": 0.6743961935,
    "Mask": "Edge",
    "Method": "EdgeRegressor",
    "Retained": false,
    "SingularValue": 77.9535167096,
    "VarianceExplained": 0.0027268345
  },
  "dropped_49": {
    "CumulativeVarianceExplained": 0.6771039975,
    "Mask": "Edge",
    "Method": "EdgeRegressor",
    "Retained": false,
    "SingularValue": 77.6810221693,
    "VarianceExplained": 0.002707804
  },
  "dropped_5": {
    "CumulativeVarianceExplained": 0.5250349321,
    "Mask": "Edge",
    "Method": "EdgeRegressor",
    "Retained": false,
    "SingularValue": 105.5070623937,
    "VarianceExplained": 0.0049951717
  },
  "dropped_50": {
    "CumulativeVarianceExplained": 0.6797957062,
    "Mask": "Edge",
    "Method": "EdgeRegressor",
    "Retained": false,
    "SingularValue": 77.4498085062,
    "VarianceExplained": 0.0026917087
  },
  "dropped_51": {
    "CumulativeVarianceExplained": 0.6824742016,
    "Mask": "Edge",
    "Method": "EdgeRegressor",
    "Retained": false,
    "SingularValue": 77.259477649,
    "VarianceExplained": 0.0026784953
  },
  "dropped_52": {
    "CumulativeVarianceExplained": 0.6851329257,
    "Mask": "Edge",
    "Method": "EdgeRegressor",
    "Retained": false,
    "SingularValue": 76.9738053475,
    "VarianceExplained": 0.0026587241
  },
  "dropped_53": {
    "CumulativeVarianceExplained": 0.6877788161,
    "Mask": "Edge",
    "Method": "EdgeRegressor",
    "Retained": false,
    "SingularValue": 76.7878037537,
    "VarianceExplained": 0.0026458904
  },
  "dropped_54": {
    "CumulativeVarianceExplained": 0.6904099012,
    "Mask": "Edge",
    "Method": "EdgeRegressor",
    "Retained": false,
    "SingularValue": 76.5726659222,
    "VarianceExplained": 0.0026310851
  },
  "dropped_55": {
    "CumulativeVarianceExplained": 0.6930234741,
    "Mask": "Edge",
    "Method": "EdgeRegressor",
    "Retained": false,
    "SingularValue": 76.3174100939,
    "VarianceExplained": 0.0026135728
  },
  "dropped_56": {
    "CumulativeVarianceExplained": 0.6956289577,
    "Mask": "Edge",
    "Method": "EdgeRegressor",
    "Retained": false,
    "SingularValue": 76.1992138828,
    "VarianceExplained": 0.0026054836
  },
  "dropped_57": {
    "CumulativeVarianceExplained": 0.6982168119,
    "Mask": "Edge",
    "Method": "EdgeRegressor",
    "Retained": false,
    "SingularValue": 75.9409843851,
    "VarianceExplained": 0.0025878542
  },
  "dropped_58": {
    "CumulativeVarianceExplained": 0.7007775476,
    "Mask": "Edge",
    "Method": "EdgeRegressor",
    "Retained": false,
    "SingularValue": 75.5420388873,
    "VarianceExplained": 0.0025607358
  },
  "dropped_59": {
    "CumulativeVarianceExplained": 0.7033340256,
    "Mask": "Edge",
    "Method": "EdgeRegressor",
    "Retained": false,
    "SingularValue": 75.4792091003,
    "VarianceExplained": 0.0025564779
  },
  "dropped_6": {
    "CumulativeVarianceExplained": 0.5298297622,
    "Mask": "Edge",
    "Method": "EdgeRegressor",
    "Retained": false,
    "SingularValue": 103.3696220583,
    "VarianceExplained": 0.00479483
  },
  "dropped_60": {
    "CumulativeVarianceExplained": 0.7058801208,
    "Mask": "Edge",
    "Method": "EdgeRegressor",
    "Retained": false,
    "SingularValue": 75.3257805254,
    "VarianceExplained": 0.0025460952
  },
  "dropped_61": {
    "CumulativeVarianceExplained": 0.7083938066,
    "Mask": "Edge",
    "Method": "EdgeRegressor",
    "Retained": false,
    "SingularValue": 74.8448321948,
    "VarianceExplained": 0.0025136858
  },
  "dropped_62": {
    "CumulativeVarianceExplained": 0.7108903449,
    "Mask": "Edge",
    "Method": "EdgeRegressor",
    "Retained": false,
    "SingularValue": 74.5891112908,
    "VarianceExplained": 0.0024965383
  },
  "dropped_63": {
    "CumulativeVarianceExplained": 0.713373513,
    "Mask": "Edge",
    "Method": "EdgeRegressor",
    "Retained": false,
    "SingularValue": 74.3891125818,
    "VarianceExplained": 0.0024831681
  },
  "dropped_64": {
    "CumulativeVarianceExplained": 0.715849786,
    "Mask": "Edge",
    "Method": "EdgeRegressor",
    "Retained": false,
    "SingularValue": 74.2857614934,
    "VarianceExplained": 0.002476273
  },
  "dropped_65": {
    "CumulativeVarianceExplained": 0.7183150514,
    "Mask": "Edge",
    "Method": "EdgeRegressor",
    "Retained": false,
    "SingularValue": 74.1204693683,
    "VarianceExplained": 0.0024652654
  },
  "dropped_66": {
    "CumulativeVarianceExplained": 0.7207560976,
    "Mask": "Edge",
    "Method": "EdgeRegressor",
    "Retained": false,
    "SingularValue": 73.7554848145,
    "VarianceExplained": 0.0024410462
  },
  "dropped_67": {
    "CumulativeVarianceExplained": 0.7231932677,
    "Mask": "Edge",
    "Method": "EdgeRegressor",
    "Retained": false,
    "SingularValue": 73.6969037892,
    "VarianceExplained": 0.0024371701
  },
  "dropped_68": {
    "CumulativeVarianceExplained": 0.7256092842,
    "Mask": "Edge",
    "Method": "EdgeRegressor",
    "Retained": false,
    "SingularValue": 73.376376103,
    "VarianceExplained": 0.0024160164
  },
  "dropped_69": {
    "CumulativeVarianceExplained": 0.728016142,
    "Mask": "Edge",
    "Method": "EdgeRegressor",
    "Retained": false,
    "SingularValue": 73.2371681464,
    "VarianceExplained": 0.0024068579
  },
  "dropped_7": {
    "CumulativeVarianceExplained": 0.5345044491,
    "Mask": "Edge",
    "Method": "EdgeRegressor",
    "Retained": false,
    "SingularValue": 102.0663498946,
    "VarianceExplained": 0.0046746869
  },
  "dropped_70": {
    "CumulativeVarianceExplained": 0.7304150851,
    "Mask": "Edge",
    "Method": "EdgeRegressor",
    "Retained": false,
    "SingularValue": 73.1166510177,
    "VarianceExplained": 0.0023989431
  },
  "dropped_71": {
    "CumulativeVarianceExplained": 0.7327988438,
    "Mask": "Edge",
    "Method": "EdgeRegressor",
    "Retained": false,
    "SingularValue": 72.8848832941,
    "VarianceExplained": 0.0023837587
  },
  "dropped_72": {
    "CumulativeVarianceExplained": 0.7351692559,
    "Mask": "Edge",
    "Method": "EdgeRegressor",
    "Retained": false,
    "SingularValue": 72.6805566302,
    "VarianceExplained": 0.0023704121
  },
  "dropped_73": {
    "CumulativeVarianceExplained": 0.7375338471,
    "Mask": "Edge",
    "Method": "EdgeRegressor",
    "Retained": false,
    "SingularValue": 72.5912641727,
    "VarianceExplained": 0.0023645913
  },
  "dropped_74": {
    "CumulativeVarianceExplained": 0.7398809991,
    "Mask": "Edge",
    "Method": "EdgeRegressor",
    "Retained": false,
    "SingularValue": 72.323082416,
    "VarianceExplained": 0.002347152
  },
  "dropped_75": {
    "CumulativeVarianceExplained": 0.7422253431,
    "Mask": "Edge",
    "Method": "EdgeRegressor",
    "Retained": false,
    "SingularValue": 72.279807156,
    "VarianceExplained": 0.002344344
  },
  "dropped_76": {
    "CumulativeVarianceExplained": 0.7445647816,
    "Mask": "Edge",
    "Method": "EdgeRegressor",
    "Retained": false,
    "SingularValue": 72.2041453522,
    "VarianceExplained": 0.0023394385
  },
  "dropped_77": {
    "CumulativeVarianceExplained": 0.7468970969,
    "Mask": "Edge",
    "Method": "EdgeRegressor",
    "Retained": false,
    "SingularValue": 72.0941383554,
    "VarianceExplained": 0.0023323154
  },
  "dropped_78": {
    "CumulativeVarianceExplained": 0.7492188759,
    "Mask": "Edge",
    "Method": "EdgeRegressor",
    "Retained": false,
    "SingularValue": 71.9311084419,
    "VarianceExplained": 0.0023217789
  },
  "dropped_79": {
    "CumulativeVarianceExplained": 0.751525484,
    "Mask": "Edge",
    "Method": "EdgeRegressor",
    "Retained": false,
    "SingularValue": 71.6957192644,
    "VarianceExplained": 0.0023066081
  },
  "dropped_8": {
    "CumulativeVarianceExplained": 0.5391169742,
    "Mask": "Edge",
    "Method": "EdgeRegressor",
    "Retained": false,
    "SingularValue": 101.3854642644,
    "VarianceExplained": 0.0046125252
  },
  "dropped_80": {
    "CumulativeVarianceExplained": 0.7538168292,
    "Mask": "Edge",
    "Method": "EdgeRegressor",
    "Retained": false,
    "SingularValue": 71.4581191167,
    "VarianceExplained": 0.0022913452
  },
  "dropped_81": {
    "CumulativeVarianceExplained": 0.7561053169,
    "Mask": "Edge",
    "Method": "EdgeRegressor",
    "Retained": false,
    "SingularValue": 71.4135478207,
    "VarianceExplained": 0.0022884877
  },
  "dropped_82": {
    "CumulativeVarianceExplained": 0.7583763632,
    "Mask": "Edge",
    "Method": "EdgeRegressor",
    "Retained": false,
    "SingularValue": 71.1408935216,
    "VarianceExplained": 0.0022710463
  },
  "dropped_83": {
    "CumulativeVarianceExplained": 0.7606386586,
    "Mask": "Edge",
    "Method": "EdgeRegressor",
    "Retained": false,
    "SingularValue": 71.0036990917,
    "VarianceExplained": 0.0022622954
  },
  "dropped_84": {
    "CumulativeVarianceExplained": 0.762893251,
    "Mask": "Edge",
    "Method": "EdgeRegressor",
    "Retained": false,
    "SingularValue": 70.8827150566,
    "VarianceExplained": 0.0022545925
  },
  "dropped_85": {
    "CumulativeVarianceExplained": 0.7651387408,
    "Mask": "Edge",
    "Method": "EdgeRegressor",
    "Retained": false,
    "SingularValue": 70.7394796851,
    "VarianceExplained": 0.0022454898
  },
  "dropped_86": {
    "CumulativeVarianceExplained": 0.7673711754,
    "Mask": "Edge",
    "Method": "EdgeRegressor",
    "Retained": false,
    "SingularValue": 70.533541213,
    "VarianceExplained": 0.0022324346
  },
  "dropped_87": {
    "CumulativeVarianceExplained": 0.7695973002,
    "Mask": "Edge",
    "Method": "EdgeRegressor",
    "Retained": false,
    "SingularValue": 70.4337927264,
    "VarianceExplained": 0.0022261248
  },
  "dropped_88": {
    "CumulativeVarianceExplained": 0.7718085281,
    "Mask": "Edge",
    "Method": "EdgeRegressor",
    "Retained": false,
    "SingularValue": 70.1977297638,
    "VarianceExplained": 0.0022112279
  },
  "dropped_89": {
    "CumulativeVarianceExplained": 0.7740154643,
    "Mask": "Edge",
    "Method": "EdgeRegressor",
    "Retained": false,
    "SingularValue": 70.1295760576,
    "VarianceExplained": 0.0022069363
  },
  "dropped_9": {
    "CumulativeVarianceExplained": 0.5436800496,
    "Mask": "Edge",
    "Method": "EdgeRegressor",
    "Retained": false,
    "SingularValue": 100.8405348099,
    "VarianceExplained": 0.0045630754
  },
  "dropped_90": {
    "CumulativeVarianceExplained": 0.7762075267,
    "Mask": "Edge",
    "Method": "EdgeRegressor",
    "Retained": false,
    "SingularValue": 69.8928534207,
    "VarianceExplained": 0.0021920624
  },
  "dropped_91": {
    "CumulativeVarianceExplained": 0.7783949392,
    "Mask": "Edge",
    "Method": "EdgeRegressor",
    "Retained": false,
    "SingularValue": 69.8186849414,
    "VarianceExplained": 0.0021874125
  },
  "dropped_92": {
    "CumulativeVarianceExplained": 0.7805760736,
    "Mask": "Edge",
    "Method": "EdgeRegressor",
    "Retained": false,
    "SingularValue": 69.7184206506,
    "VarianceExplained": 0.0021811345
  },
  "dropped_93": {
    "CumulativeVarianceExplained": 0.7827438,
    "Mask": "Edge",
    "Method": "EdgeRegressor",
    "Retained": false,
    "SingularValue": 69.5037993384,
    "VarianceExplained": 0.0021677263
  },
  "dropped_94": {
    "CumulativeVarianceExplained": 0.7848968585,
    "Mask": "Edge",
    "Method": "EdgeRegressor",
    "Retained": false,
    "SingularValue": 69.2682532837,
    "VarianceExplained": 0.0021530585
  },
  "dropped_95": {
    "CumulativeVarianceExplained": 0.7870459877,
    "Mask": "Edge",
    "Method": "EdgeRegressor",
    "Retained": false,
    "SingularValue": 69.2050178014,
    "VarianceExplained": 0.0021491292
  },
  "dropped_96": {
    "CumulativeVarianceExplained": 0.7891904621,
    "Mask": "Edge",
    "Method": "EdgeRegressor",
    "Retained": false,
    "SingularValue": 69.1300312545,
    "VarianceExplained": 0.0021444744
  },
  "dropped_97": {
    "CumulativeVarianceExplained": 0.7913273759,
    "Mask": "Edge",
    "Method": "EdgeRegressor",
    "Retained": false,
    "SingularValue": 69.0080606184,
    "VarianceExplained": 0.0021369138
  },
  "dropped_98": {
    "CumulativeVarianceExplained": 0.793452759,
    "Mask": "Edge",
    "Method": "EdgeRegressor",
    "Retained": false,
    "SingularValue": 68.8216258815,
    "VarianceExplained": 0.0021253831
  },
  "dropped_99": {
    "CumulativeVarianceExplained": 0.7955712918,
    "Mask": "Edge",
    "Method": "EdgeRegressor",
    "Retained": false,
    "SingularValue": 68.7106270808,
    "VarianceExplained": 0.0021185328
  },
  "edge_comp_00": {
    "CumulativeVarianceExplained": 0.1456379774,
    "Mask": "Edge",
    "Method": "EdgeRegressor",
    "Retained": true,
    "SingularValue": 569.6966145656,
    "VarianceExplained": 0.1456379774
  },
  "edge_comp_01": {
    "CumulativeVarianceExplained": 0.2002681887,
    "Mask": "Edge",
    "Method": "EdgeRegressor",
    "Retained": true,
    "SingularValue": 348.917505783,
    "VarianceExplained": 0.0546302113
  },
  "edge_comp_02": {
    "CumulativeVarianceExplained": 0.236105662,
    "Mask": "Edge",
    "Method": "EdgeRegressor",
    "Retained": true,
    "SingularValue": 282.6018566194,
    "VarianceExplained": 0.0358374734
  },
  "edge_comp_03": {
    "CumulativeVarianceExplained": 0.2634214827,
    "Mask": "Edge",
    "Method": "EdgeRegressor",
    "Retained": true,
    "SingularValue": 246.725163788,
    "VarianceExplained": 0.0273158207
  },
  "edge_comp_04": {
    "CumulativeVarianceExplained": 0.2887143693,
    "Mask": "Edge",
    "Method": "EdgeRegressor",
    "Retained": true,
    "SingularValue": 237.4135584695,
    "VarianceExplained": 0.0252928866
  },
  "edge_comp_05": {
    "CumulativeVarianceExplained": 0.3111466446,
    "Mask": "Edge",
    "Method": "EdgeRegressor",
    "Retained": true,
    "SingularValue": 223.5851637228,
    "VarianceExplained": 0.0224322753
  },
  "edge_comp_06": {
    "CumulativeVarianceExplained": 0.3307744895,
    "Mask": "Edge",
    "Method": "EdgeRegressor",
    "Retained": true,
    "SingularValue": 209.1426604434,
    "VarianceExplained": 0.0196278449
  },
  "edge_comp_07": {
    "CumulativeVarianceExplained": 0.3487325475,
    "Mask": "Edge",
    "Method": "EdgeRegressor",
    "Retained": true,
    "SingularValue": 200.0488245539,
    "VarianceExplained": 0.017958058
  },
  "edge_comp_08": {
    "CumulativeVarianceExplained": 0.3639368874,
    "Mask": "Edge",
    "Method": "EdgeRegressor",
    "Retained": true,
    "SingularValue": 184.0730060689,
    "VarianceExplained": 0.0152043399
  },
  "edge_comp_09": {
    "CumulativeVarianceExplained": 0.3772011612,
    "Mask": "Edge",
    "Method": "EdgeRegressor",
    "Retained": true,
    "SingularValue": 171.9285726822,
    "VarianceExplained": 0.0132642738
  },
  "edge_comp_10": {
    "CumulativeVarianceExplained": 0.3890341904,
    "Mask": "Edge",
    "Method": "EdgeRegressor",
    "Retained": true,
    "SingularValue": 162.3881323049,
    "VarianceExplained": 0.0118330292
  },
  "edge_comp_11": {
    "CumulativeVarianceExplained": 0.4006812447,
    "Mask": "Edge",
    "Method": "EdgeRegressor",
    "Retained": true,
    "SingularValue": 161.10698443,
    "VarianceExplained": 0.0116470543
  },
  "edge_comp_12": {
    "CumulativeVarianceExplained": 0.4102523688,
    "Mask": "Edge",
    "Method": "EdgeRegressor",
    "Retained": true,
    "SingularValue": 146.0453705215,
    "VarianceExplained": 0.0095711242
  },
  "edge_comp_13": {
    "CumulativeVarianceExplained": 0.4195245948,
    "Mask": "Edge",
    "Method": "EdgeRegressor",
    "Retained": true,
    "SingularValue": 143.7468453984,
    "VarianceExplained": 0.009272226
  },
  "edge_comp_14": {
    "CumulativeVarianceExplained": 0.4285065335,
    "Mask": "Edge",
    "Method": "EdgeRegressor",
    "Retained": true,
    "SingularValue": 141.4787985098,
    "VarianceExplained": 0.0089819387
  },
  "edge_comp_15": {
    "CumulativeVarianceExplained": 0.4369340945,
    "Mask": "Edge",
    "Method": "EdgeRegressor",
    "Retained": true,
    "SingularValue": 137.0431309646,
    "VarianceExplained": 0.008427561
  },
  "edge_comp_16": {
    "CumulativeVarianceExplained": 0.4449279832,
    "Mask": "Edge",
    "Method": "EdgeRegressor",
    "Retained": true,
    "SingularValue": 133.4705241761,
    "VarianceExplained": 0.0079938886
  },
  "edge_comp_17": {
    "CumulativeVarianceExplained": 0.4526823203,
    "Mask": "Edge",
    "Method": "EdgeRegressor",
    "Retained": true,
    "SingularValue": 131.4554683379,
    "VarianceExplained": 0.0077543371
  },
  "edge_comp_18": {
    "CumulativeVarianceExplained": 0.4600846617,
    "Mask": "Edge",
    "Method": "EdgeRegressor",
    "Retained": true,
    "SingularValue": 128.437213968,
    "VarianceExplained": 0.0074023415
  },
  "edge_comp_19": {
    "CumulativeVarianceExplained": 0.466990793,
    "Mask": "Edge",
    "Method": "EdgeRegressor",
    "Retained": true,
    "SingularValue": 124.0577027167,
    "VarianceExplained": 0.0069061313
  },
  "edge_comp_20": {
    "CumulativeVarianceExplained": 0.473742241,
    "Mask": "Edge",
    "Method": "EdgeRegressor",
    "Retained": true,
    "SingularValue": 122.6605143505,
    "VarianceExplained": 0.006751448
  },
  "edge_comp_21": {
    "CumulativeVarianceExplained": 0.4802850077,
    "Mask": "Edge",
    "Method": "EdgeRegressor",
    "Retained": true,
    "SingularValue": 120.7499720972,
    "VarianceExplained": 0.0065427668
  },
  "edge_comp_22": {
    "CumulativeVarianceExplained": 0.4866141093,
    "Mask": "Edge",
    "Method": "EdgeRegressor",
    "Retained": true,
    "SingularValue": 118.7619587777,
    "VarianceExplained": 0.0063291016
  },
  "edge_comp_23": {
    "CumulativeVarianceExplained": 0.4928125222,
    "Mask": "Edge",
    "Method": "EdgeRegressor",
    "Retained": true,
    "SingularValue": 117.5294134789,
    "VarianceExplained": 0.0061984128
  },
  "framewise_displacement": {
    "Units": "mm"
  },
  "rot_x": {
    "Description": "Rotation about left-right axis. Also known as \"pitch\".",
    "Units": "rad"
  },
  "rot_y": {
    "Description": "Rotation about anterior-posterior axis. Also known as \"roll\".",
    "Units": "rad"
  },
  "rot_z": {
    "Description": "Rotation about superior-inferior axis. Also known as \"yaw\".",
    "Units": "rad"
  },
  "t_comp_cor_00": {
    "CumulativeVarianceExplained": 0.258911337,
    "Method": "tCompCor",
    "Retained": true,
    "SingularValue": 184.5178604363,
    "VarianceExplained": 0.258911337
  },
  "t_comp_cor_01": {
    "CumulativeVarianceExplained": 0.3817251468,
    "Method": "tCompCor",
    "Retained": true,
    "SingularValue": 127.0827131849,
    "VarianceExplained": 0.1228138098
  },
  "t_comp_cor_02": {
    "CumulativeVarianceExplained": 0.4850228368,
    "Method": "tCompCor",
    "Retained": true,
    "SingularValue": 116.5489005858,
    "VarianceExplained": 0.1032976899
  },
  "t_comp_cor_03": {
    "CumulativeVarianceExplained": 0.5397127356,
    "Method": "tCompCor",
    "Retained": true,
    "SingularValue": 84.804019322,
    "VarianceExplained": 0.0546898988
  },
  "trans_x": {
    "Description": "Translation along left-right axis.",
    "Units": "mm"
  },
  "trans_y": {
    "Description": "Translation along anterior-posterior axis.",
    "Units": "mm"
  },
  "trans_z": {
    "Description": "Translation along superior-inferior axis.",
    "Units": "mm"
  },
  "w_comp_cor_00": {
    "CumulativeVarianceExplained": 0.1258154883,
    "Mask": "WM",
    "Method": "aCompCor",
    "Retained": true,
    "SingularValue": 160.305375738,
    "VarianceExplained": 0.1258154883
  },
  "w_comp_cor_01": {
    "CumulativeVarianceExplained": 0.1704672419,
    "Mask": "WM",
    "Method": "aCompCor",
    "Retained": true,
    "SingularValue": 95.4993228987,
    "VarianceExplained": 0.0446517536
  },
  "w_comp_cor_02": {
    "CumulativeVarianceExplained": 0.193336863,
    "Mask": "WM",
    "Method": "aCompCor",
    "Retained": true,
    "SingularValue": 68.3455931519,
    "VarianceExplained": 0.0228696211
  },
  "w_comp_cor_03": {
    "CumulativeVarianceExplained": 0.2120066413,
    "Mask": "WM",
    "Method": "aCompCor",
    "Retained": true,
    "SingularValue": 61.7519410372,
    "VarianceExplained": 0.0186697783
  },
  "w_comp_cor_04": {
    "CumulativeVarianceExplained": 0.2292363665,
    "Mask": "WM",
    "Method": "aCompCor",
    "Retained": true,
    "SingularValue": 59.3226041973,
    "VarianceExplained": 0.0172297252
  },
  "w_comp_cor_05": {
    "CumulativeVarianceExplained": 0.2450394323,
    "Mask": "WM",
    "Method": "aCompCor",
    "Retained": true,
    "SingularValue": 56.8135212467,
    "VarianceExplained": 0.0158030658
  },
  "w_comp_cor_06": {
    "CumulativeVarianceExplained": 0.2601632066,
    "Mask": "WM",
    "Method": "aCompCor",
    "Retained": true,
    "SingularValue": 55.5790508082,
    "VarianceExplained": 0.0151237742
  },
  "w_comp_cor_07": {
    "CumulativeVarianceExplained": 0.2740950785,
    "Mask": "WM",
    "Method": "aCompCor",
    "Retained": true,
    "SingularValue": 53.3440234737,
    "VarianceExplained": 0.0139318719
  },
  "w_comp_cor_08": {
    "CumulativeVarianceExplained": 0.2873250958,
    "Mask": "WM",
    "Method": "aCompCor",
    "Retained": true,
    "SingularValue": 51.9829879549,
    "VarianceExplained": 0.0132300173
  },
  "w_comp_cor_09": {
    "CumulativeVarianceExplained": 0.2997852117,
    "Mask": "WM",
    "Method": "aCompCor",
    "Retained": true,
    "SingularValue": 50.4477815921,
    "VarianceExplained": 0.0124601159
  },
  "w_comp_cor_10": {
    "CumulativeVarianceExplained": 0.3112146769,
    "Mask": "WM",
    "Method": "aCompCor",
    "Retained": true,
    "SingularValue": 48.316335414,
    "VarianceExplained": 0.0114294652
  },
  "w_comp_cor_11": {
    "CumulativeVarianceExplained": 0.3221478582,
    "Mask": "WM",
    "Method": "aCompCor",
    "Retained": true,
    "SingularValue": 47.2557116048,
    "VarianceExplained": 0.0109331813
  },
  "w_comp_cor_12": {
    "CumulativeVarianceExplained": 0.3323879121,
    "Mask": "WM",
    "Method": "aCompCor",
    "Retained": true,
    "SingularValue": 45.7332593994,
    "VarianceExplained": 0.0102400539
  },
  "w_comp_cor_13": {
    "CumulativeVarianceExplained": 0.3423782219,
    "Mask": "WM",
    "Method": "aCompCor",
    "Retained": true,
    "SingularValue": 45.1721239172,
    "VarianceExplained": 0.0099903098
  },
  "w_comp_cor_14": {
    "CumulativeVarianceExplained": 0.3519274203,
    "Mask": "WM",
    "Method": "aCompCor",
    "Retained": true,
    "SingularValue": 44.1636022033,
    "VarianceExplained": 0.0095491983
  },
  "w_comp_cor_15": {
    "CumulativeVarianceExplained": 0.3610624999,
    "Mask": "WM",
    "Method": "aCompCor",
    "Retained": true,
    "SingularValue": 43.1953702855,
    "VarianceExplained": 0.0091350796
  },
  "w_comp_cor_16": {
    "CumulativeVarianceExplained": 0.3693371615,
    "Mask": "WM",
    "Method": "aCompCor",
    "Retained": true,
    "SingularValue": 41.1108213506,
    "VarianceExplained": 0.0082746616
  },
  "w_comp_cor_17": {
    "CumulativeVarianceExplained": 0.3774740605,
    "Mask": "WM",
    "Method": "aCompCor",
    "Retained": true,
    "SingularValue": 40.767163559,
    "VarianceExplained": 0.008136899
  },
  "w_comp_cor_18": {
    "CumulativeVarianceExplained": 0.3854109214,
    "Mask": "WM",
    "Method": "aCompCor",
    "Retained": true,
    "SingularValue": 40.2629336777,
    "VarianceExplained": 0.0079368608
  },
  "w_comp_cor_19": {
    "CumulativeVarianceExplained": 0.3931465113,
    "Mask": "WM",
    "Method": "aCompCor",
    "Retained": true,
    "SingularValue": 39.7491414699,
    "VarianceExplained": 0.00773559
  },
  "w_comp_cor_20": {
    "CumulativeVarianceExplained": 0.4007419952,
    "Mask": "WM",
    "Method": "aCompCor",
    "Retained": true,
    "SingularValue": 39.387530929,
    "VarianceExplained": 0.0075954839
  },
  "w_comp_cor_21": {
    "CumulativeVarianceExplained": 0.4081475951,
    "Mask": "WM",
    "Method": "aCompCor",
    "Retained": true,
    "SingularValue": 38.8920784778,
    "VarianceExplained": 0.0074055998
  },
  "w_comp_cor_22": {
    "CumulativeVarianceExplained": 0.4154787132,
    "Mask": "WM",
    "Method": "aCompCor",
    "Retained": true,
    "SingularValue": 38.6960059183,
    "VarianceExplained": 0.0073311181
  },
  "w_comp_cor_23": {
    "CumulativeVarianceExplained": 0.4225229438,
    "Mask": "WM",
    "Method": "aCompCor",
    "Retained": true,
    "SingularValue": 37.931307667,
    "VarianceExplained": 0.0070442306
  },
  "w_comp_cor_24": {
    "CumulativeVarianceExplained": 0.4294486099,
    "Mask": "WM",
    "Method": "aCompCor",
    "Retained": true,
    "SingularValue": 37.6107339516,
    "VarianceExplained": 0.0069256661
  },
  "w_comp_cor_25": {
    "CumulativeVarianceExplained": 0.4363223126,
    "Mask": "WM",
    "Method": "aCompCor",
    "Retained": true,
    "SingularValue": 37.4693711463,
    "VarianceExplained": 0.0068737027
  },
  "w_comp_cor_26": {
    "CumulativeVarianceExplained": 0.4431247449,
    "Mask": "WM",
    "Method": "aCompCor",
    "Retained": true,
    "SingularValue": 37.2746133302,
    "VarianceExplained": 0.0068024323
  },
  "w_comp_cor_27": {
    "CumulativeVarianceExplained": 0.4497648693,
    "Mask": "WM",
    "Method": "aCompCor",
    "Retained": true,
    "SingularValue": 36.8272371217,
    "VarianceExplained": 0.0066401243
  },
  "w_comp_cor_28": {
    "CumulativeVarianceExplained": 0.4562392623,
    "Mask": "WM",
    "Method": "aCompCor",
    "Retained": true,
    "SingularValue": 36.364746376,
    "VarianceExplained": 0.006474393
  },
  "w_comp_cor_29": {
    "CumulativeVarianceExplained": 0.4626234624,
    "Mask": "WM",
    "Method": "aCompCor",
    "Retained": true,
    "SingularValue": 36.1105645894,
    "VarianceExplained": 0.0063842001
  },
  "w_comp_cor_30": {
    "CumulativeVarianceExplained": 0.4688662742,
    "Mask": "WM",
    "Method": "aCompCor",
    "Retained": true,
    "SingularValue": 35.7084626089,
    "VarianceExplained": 0.0062428118
  },
  "w_comp_cor_31": {
    "CumulativeVarianceExplained": 0.4750296093,
    "Mask": "WM",
    "Method": "aCompCor",
    "Retained": true,
    "SingularValue": 35.4804340893,
    "VarianceExplained": 0.0061633351
  },
  "w_comp_cor_32": {
    "CumulativeVarianceExplained": 0.4811363582,
    "Mask": "WM",
    "Method": "aCompCor",
    "Retained": true,
    "SingularValue": 35.3171835553,
    "VarianceExplained": 0.0061067489
  },
  "w_comp_cor_33": {
    "CumulativeVarianceExplained": 0.4871906688,
    "Mask": "WM",
    "Method": "aCompCor",
    "Retained": true,
    "SingularValue": 35.1652235299,
    "VarianceExplained": 0.0060543106
  },
  "w_comp_cor_34": {
    "CumulativeVarianceExplained": 0.4931695713,
    "Mask": "WM",
    "Method": "aCompCor",
    "Retained": true,
    "SingularValue": 34.9455408861,
    "VarianceExplained": 0.0059789025
  },
  "w_comp_cor_35": {
    "CumulativeVarianceExplained": 0.4990629415,
    "Mask": "WM",
    "Method": "aCompCor",
    "Retained": true,
    "SingularValue": 34.6946805969,
    "VarianceExplained": 0.0058933702
  },
  "w_comp_cor_36": {
    "CumulativeVarianceExplained": 0.504803063,
    "Mask": "WM",
    "Method": "aCompCor",
    "Retained": true,
    "SingularValue": 34.2406166298,
    "VarianceExplained": 0.0057401216
  }
}